{"cameraMode":{"drawMode":0,"name":"Shaded","section":"Shading Mode"},"sceneLighting":true,"audioPlay":false,"sceneViewState":{"showFog":true,"showMaterialUpdate":true,"showSkybox":true,"showFlares":true,"showImageEffects":true,"showParticleSystems":true,"showVisualEffectGraphs":true},"in2DMode":false,"pivot":{"x":-6.2333831787109379,"y":4.204345703125,"z":-4.932558059692383},"rotation":{"x":-0.11656985431909561,"y":0.6962116360664368,"z":-0.11615036427974701,"w":-0.6987250447273254},"size":40.8470344543457,"orthographic":false}